odoo/addons/partner_multi_company/README.rst
odoo/addons/partner_multi_company/__init__.py
odoo/addons/partner_multi_company/__manifest__.py
odoo/addons/partner_multi_company/hooks.py
odoo/addons/partner_multi_company/i18n/de.po
odoo/addons/partner_multi_company/i18n/es.po
odoo/addons/partner_multi_company/i18n/fr.po
odoo/addons/partner_multi_company/i18n/hr.po
odoo/addons/partner_multi_company/i18n/it.po
odoo/addons/partner_multi_company/i18n/partner_multi_company.pot
odoo/addons/partner_multi_company/i18n/pt.po
odoo/addons/partner_multi_company/migrations/13.0.1.0.0/pre-migration.py
odoo/addons/partner_multi_company/models/__init__.py
odoo/addons/partner_multi_company/models/res_company.py
odoo/addons/partner_multi_company/models/res_config_settings.py
odoo/addons/partner_multi_company/models/res_partner.py
odoo/addons/partner_multi_company/models/res_users.py
odoo/addons/partner_multi_company/readme/CONTRIBUTORS.rst
odoo/addons/partner_multi_company/readme/DESCRIPTION.rst
odoo/addons/partner_multi_company/readme/INSTALL.rst
odoo/addons/partner_multi_company/readme/ROADMAP.rst
odoo/addons/partner_multi_company/readme/USAGE.rst
odoo/addons/partner_multi_company/static/description/icon.png
odoo/addons/partner_multi_company/static/description/index.html
odoo/addons/partner_multi_company/tests/__init__.py
odoo/addons/partner_multi_company/tests/test_partner_multi_company.py
odoo/addons/partner_multi_company/views/res_config_settings.xml
odoo/addons/partner_multi_company/views/res_partner_view.xml
odoo14_addon_partner_multi_company-14.0.1.1.0.dist-info/METADATA
odoo14_addon_partner_multi_company-14.0.1.1.0.dist-info/WHEEL
odoo14_addon_partner_multi_company-14.0.1.1.0.dist-info/top_level.txt
odoo14_addon_partner_multi_company-14.0.1.1.0.dist-info/RECORD
